MANIFEST.in
README.md
setup.cfg
setup.json
setup.py
aiida_lsmo/__init__.py
aiida_lsmo.egg-info/PKG-INFO
aiida_lsmo.egg-info/SOURCES.txt
aiida_lsmo.egg-info/dependency_links.txt
aiida_lsmo.egg-info/entry_points.txt
aiida_lsmo.egg-info/requires.txt
aiida_lsmo.egg-info/top_level.txt
aiida_lsmo/calcfunctions/__init__.py
aiida_lsmo/calcfunctions/ff_builder_module.py
aiida_lsmo/calcfunctions/ff_data.yaml
aiida_lsmo/calcfunctions/selectivity.py
aiida_lsmo/calcfunctions/working_cap.py
aiida_lsmo/calcfunctions/wrappers.py
aiida_lsmo/parsers/__init__.py
aiida_lsmo/parsers/parser_functions.py
aiida_lsmo/utils/__init__.py
aiida_lsmo/utils/cp2k_utils.py
aiida_lsmo/utils/multiply_unitcell.py
aiida_lsmo/utils/other_utilities.py
aiida_lsmo/workchains/__init__.py
aiida_lsmo/workchains/binding_site.py
aiida_lsmo/workchains/cp2k_binding_energy.py
aiida_lsmo/workchains/cp2k_multistage.py
aiida_lsmo/workchains/cp2k_multistage_ddec.py
aiida_lsmo/workchains/isotherm.py
aiida_lsmo/workchains/isotherm_calc_pe.py
aiida_lsmo/workchains/isotherm_multi_temp.py
aiida_lsmo/workchains/nanoporous_screening_1.py
aiida_lsmo/workchains/sim_annealing.py
aiida_lsmo/workchains/zeopp_multistage_ddec.py
aiida_lsmo/workchains/cp2k_multistage_protocols/robust_conv.yaml
aiida_lsmo/workchains/cp2k_multistage_protocols/singlepoint.yaml
aiida_lsmo/workchains/cp2k_multistage_protocols/standard.yaml
aiida_lsmo/workchains/cp2k_multistage_protocols/test.yaml
aiida_lsmo/workchains/isotherm_data/DEFAULT.rad
aiida_lsmo/workchains/isotherm_data/DREIDING.rad
aiida_lsmo/workchains/isotherm_data/UFF.rad
aiida_lsmo/workchains/isotherm_data/isotherm_molecules.yaml
tests/__init__.py
tests/test_isotherm_workchain.py
tests/test_parsers.py