Metadata-Version: 2.1
Name: aiida-lsmo
Version: 1.0.0
Summary: AiiDA workflows for the LSMO laboratory at EPFL
Home-page: https://github.com/lsmo-epfl/aiida-lsmo
Author: Aliaksandr Yakutovich, Daniele Ongari, Leopold Talirz
Author-email: aliaksandr.yakutovich@epfl.ch
License: MIT License
Platform: UNKNOWN
Classifier: Programming Language :: Python :: 3.6
Classifier: Programming Language :: Python :: 3.7
Provides-Extra: testing
Provides-Extra: pre-commit
Provides-Extra: docs
